Workbook

Sheet Tiers
A1: LGB — prijsarchitectuur (AUD), gericht op conversie
A2: Blauwe cellen zijn de enige die je hier aanpast. Voorstel, Samenvatting en Marge rekenen hierop door.
A3: Groep | B3: Nieuwe prijs | C3: In euro | D3: Nu in de store
A4: Tops & blouses | B4: 44.95 | C4: =B4*$B$19 -> 27.909455 | D4: 71 producten, A$34.95 – A$69.95 (mediaan A$44.95)
A5: Swimwear | B5: 44.95 | C5: =B5*$B$19 -> 27.909455 | D5: 5 producten, A$44.95 – A$44.95 (mediaan A$44.95)
A6: Shorts & rokken | B6: 44.95 | C6: =B6*$B$19 -> 27.909455 | D6: 28 producten, A$34.95 – A$69.95 (mediaan A$44.95)
A7: Sandalen & slippers | B7: 49.95 | C7: =B7*$B$19 -> 31.013955 | D7: 26 producten, A$49.95 – A$54.95 (mediaan A$54.95)
A8: Broeken | B8: 54.95 | C8: =B8*$B$19 -> 34.118455 | D8: 9 producten, A$44.95 – A$59.95 (mediaan A$59.95)
A9: Knitwear & cardigans | B9: 54.95 | C9: =B9*$B$19 -> 34.118455 | D9: 6 producten, A$59.95 – A$59.95 (mediaan A$59.95)
A10: Platte schoenen & loafers | B10: 54.95 | C10: =B10*$B$19 -> 34.118455 | D10: 24 producten, A$54.95 – A$64.95 (mediaan A$64.95)
A11: Jurken | B11: 59.95 | C11: =B11*$B$19 -> 37.222955 | D11: 107 producten, A$49.95 – A$69.95 (mediaan A$69.95)
A12: Hakken | B12: 59.95 | C12: =B12*$B$19 -> 37.222955 | D12: 15 producten, A$64.95 – A$64.95 (mediaan A$64.95)
A13: Sneakers | B13: 59.95 | C13: =B13*$B$19 -> 37.222955 | D13: 4 producten, A$69.95 – A$69.95 (mediaan A$69.95)
A14: Boots | B14: 69.95 | C14: =B14*$B$19 -> 43.431955 | D14: 13 producten, A$59.95 – A$79.95 (mediaan A$79.95)
A15: Outerwear | B15: 74.95 | C15: =B15*$B$19 -> 46.536455 | D15: 8 producten, A$69.95 – A$89.95 (mediaan A$89.95)
A17: Instellingen
A18: Uniforme korting gebruiken? (ja/nee) | B18: nee
A19: Koers AUD naar EUR | B19: 0.6209
A20: Uniforme korting | B20: 0.45
A22: Aannames
A23: Bron: products_export_1.csv, geleverd door Justin op 20-09-2026 — 316 producten, 9.022 varianten, alle varianten van een product hebben dezelfde prijs.
A24: Koers 1 AUD = 0,6209 EUR (exchange-rates.org, 18-09-2026). Alleen om te toetsen of een prijs in euro nog redelijk is; de store rekent in AUD.
A25: Elke prijs eindigt op ,95. Compare-at wordt naar boven afgerond op een heel dollarbedrag min A$0,05, dus die eindigt ook op ,95.
A26: Geen verkoop- of inkoopdata in de export. De margeberekening op het tabblad Marge werkt met percentages die jij zelf invult.
A27: 15 van de 316 producten hebben "Men's" in de titel terwijl LGB een dames-store is — zie de opmerking in Samenvatting.

Sheet Voorstel
A1: LGB — prijsvoorstel per product
A2: Geel = door jou aan te passen. Vul "Handmatig" alleen als je van de tierprijs wilt afwijken.
A3: Handle | B3: Titel | C3: Groep | D3: Huidige prijs | E3: Tierprijs | F3: Handmatig | G3: Nieuwe prijs | H3: Verschil | I3: Verschil % | J3: Actie | K3: Let op | L3: Nieuw in euro | M3: Huidige compare-at | N3: Huidige korting | O3: Doelkorting | P3: Nieuwe compare-at | Q3: Nieuwe korting | R3: Varianten
A4: mens-tank-top-hooded-v-neck-sleeveless-zip-closure | B4: Men's Tank Top | Hooded V-Neck Sleeveless Zip Closure | C4: Tops & blouses | D4: 44.95 | E4: =IFERROR(INDEX(Tiers!$B$4:$B$15,MATCH(C4,Tiers!$A$4:$A$15,0)),D4) -> 44.95 | G4: =IF(F4="",E4,F4) -> 44.95 | H4: =G4-D4 -> 0 | I4: =IFERROR((G4-D4)/D4,0) -> 0 | J4: =IF(G4>D4,"Omhoog",IF(G4<D4,"Omlaag","Gelijk")) -> Gelijk | K4: =IF(ABS(I4)>=0.2,"controleren","") | L4: =G4*Tiers!$B$19 -> 27.909455 | M4: 81.73 | N4: =IFERROR(1-D4/M4,0) -> 0.45001835 | O4: =IF(Tiers!$B$18="ja",Tiers!$B$20,N4) -> 0.45001835 | P4: =ROUNDUP(G4/(1-O4),0)-0.05 -> 81.95 | Q4: =IFERROR(1-G4/P4,0) -> 0.45149481 | R4: 25
A5: mens-tank-top-v-neck-sleeveless-knit-relaxed | B5: Men's Tank Top | V-Neck Sleeveless Knit Relaxed | C5: Tops & blouses | D5: 44.95 | E5: =IFERROR(INDEX(Tiers!$B$4:$B$15,MATCH(C5,Tiers!$A$4:$A$15,0)),D5) -> 44.95 | G5: =IF(F5="",E5,F5) -> 44.95 | H5: =G5-D5 -> 0 | I5: =IFERROR((G5-D5)/D5,0) -> 0 | J5: =IF(G5>D5,"Omhoog",IF(G5<D5,"Omlaag","Gelijk")) -> Gelijk | K5: =IF(ABS(I5)>=0.2,"controleren","") | L5: =G5*Tiers!$B$19 -> 27.909455 | M5: 74.92 | N5: =IFERROR(1-D5/M5,0) -> 0.4000267 | O5: =IF(Tiers!$B$18="ja",Tiers!$B$20,N5) -> 0.4000267 | P5: =ROUNDUP(G5/(1-O5),0)-0.05 -> 74.95 | Q5: =IFERROR(1-G5/P5,0) -> 0.40026684 | R5: 15
A6: womens-bikini-cover-up-mesh-knit-scalloped-hem-loose-fit | B6: Women's Bikini Cover Up | Mesh Knit Scalloped Hem Loose Fit | C6: Tops & blouses | D6: 64.95 | E6: =IFERROR(INDEX(Tiers!$B$4:$B$15,MATCH(C6,Tiers!$A$4:$A$15,0)),D6) -> 44.95 | G6: =IF(F6="",E6,F6) -> 44.95 | H6: =G6-D6 -> -20 | I6: =IFERROR((G6-D6)/D6,0) -> -0.30792918 | J6: =IF(G6>D6,"Omhoog",IF(G6<D6,"Omlaag","Gelijk")) -> Omlaag | K6: =IF(ABS(I6)>=0.2,"controleren","") -> controleren | L6: =G6*Tiers!$B$19 -> 27.909455 | M6: 108.25 | N6: =IFERROR(1-D6/M6,0) -> 0.4 | O6: =IF(Tiers!$B$18="ja",Tiers!$B$20,N6) -> 0.4 | P6: =ROUNDUP(G6/(1-O6),0)-0.05 -> 74.95 | Q6: =IFERROR(1-G6/P6,0) -> 0.40026684 | R6: 18
A7: womens-bikini-cover-up-midi-length-button-front-long-sleeve | B7: Women's Bikini Cover Up | Midi Length Button Front Long Sleeve | C7: Tops & blouses | D7: 64.95 | E7: =IFERROR(INDEX(Tiers!$B$4:$B$15,MATCH(C7,Tiers!$A$4:$A$15,0)),D7) -> 44.95 | G7: =IF(F7="",E7,F7) -> 44.95 | H7: =G7-D7 -> -20 | I7: =IFERROR((G7-D7)/D7,0) -> -0.30792918 | J7: =IF(G7>D7,"Omhoog",IF(G7<D7,"Omlaag","Gelijk")) -> Omlaag | K7: =IF(ABS(I7)>=0.2,"controleren","") -> controleren | L7: =G7*Tiers!$B$19 -> 27.909455 | M7: 108.25 | N7: =IFERROR(1-D7/M7,0) -> 0.4 | O7: =IF(Tiers!$B$18="ja",Tiers!$B$20,N7) -> 0.4 | P7: =ROUNDUP(G7/(1-O7),0)-0.05 -> 74.95 | Q7: =IFERROR(1-G7/P7,0) -> 0.40026684 | R7: 56
A8: womens-bikini-cover-up-midi-mesh-knit-long-sleeve-scalloped | B8: Women's Bikini Cover Up | Midi Mesh Knit Long Sleeve Scalloped | C8: Tops & blouses | D8: 64.95 | E8: =IFERROR(INDEX(Tiers!$B$4:$B$15,MATCH(C8,Tiers!$A$4:$A$15,0)),D8) -> 44.95 | G8: =IF(F8="",E8,F8) -> 44.95 | H8: =G8-D8 -> -20 | I8: =IFERROR((G8-D8)/D8,0) -> -0.30792918 | J8: =IF(G8>D8,"Omhoog",IF(G8<D8,"Omlaag","Gelijk")) -> Omlaag | K8: =IF(ABS(I8)>=0.2,"controleren","") -> controleren | L8: =G8*Tiers!$B$19 -> 27.909455 | M8: 129.9 | N8: =IFERROR(1-D8/M8,0) -> 0.5 | O8: =IF(Tiers!$B$18="ja",Tiers!$B$20,N8) -> 0.5 | P8: =ROUNDUP(G8/(1-O8),0)-0.05 -> 89.95 | Q8: =IFERROR(1-G8/P8,0) -> 0.50027793 | R8: 18
A9: womens-bikini-cover-up-v-neck-long-sleeve-tie-front-print | B9: Women's Bikini Cover Up | V-Neck Long Sleeve Tie Front Print | C9: Tops & blouses | D9: 59.95 | E9: =IFERROR(INDEX(Tiers!$B$4:$B$15,MATCH(C9,Tiers!$A$4:$A$15,0)),D9) -> 44.95 | G9: =IF(F9="",E9,F9) -> 44.95 | H9: =G9-D9 -> -15 | I9: =IFERROR((G9-D9)/D9,0) -> -0.25020851 | J9: =IF(G9>D9,"Omhoog",IF(G9<D9,"Omlaag","Gelijk")) -> Omlaag | K9: =IF(ABS(I9)>=0.2,"controleren","") -> controleren | L9: =G9*Tiers!$B$19 -> 27.909455 | M9: 99.92 | N9: =IFERROR(1-D9/M9,0) -> 0.40002002 | O9: =IF(Tiers!$B$18="ja",Tiers!$B$20,N9) -> 0.40002002 | P9: =ROUNDUP(G9/(1-O9),0)-0.05 -> 74.95 | Q9: =IFERROR(1-G9/P9,0) -> 0.40026684 | R9: 16
A10: womens-bikini-cover-up-v-neck-striped-short-sleeve-midi | B10: Women's Bikini Cover Up | V-Neck Striped Short Sleeve Midi | C10: Tops & blouses | D10: 64.95 | E10: =IFERROR(INDEX(Tiers!$B$4:$B$15,MATCH(C10,Tiers!$A$4:$A$15,0)),D10) -> 44.95 | G10: =IF(F10="",E10,F10) -> 44.95 | H10: =G10-D10 -> -20 | I10: =IFERROR((G10-D10)/D10,0) -> -0.30792918 | J10: =IF(G10>D10,"Omhoog",IF(G10<D10,"Omlaag","Gelijk")) -> Omlaag | K10: =IF(ABS(I10)>=0.2,"controleren","") -> controleren | L10: =G10*Tiers!$B$19 -> 27.909455 | M10: 118.09 | N10: =IFERROR(1-D10/M10,0) -> 0.44999577 | O10: =IF(Tiers!$B$18="ja",Tiers!$B$20,N10) -> 0.44999577 | P10: =ROUNDUP(G10/(1-O10),0)-0.05 -> 81.95 | Q10: =IFERROR(1-G10/P10,0) -> 0.45149481 | R10: 20
A11: womens-bikini-cover-up-v-neck-three-quarter-sleeve-linen-tie-front | B11: Women's Bikini Cover Up | V-Neck Three-Quarter Sleeve Linen Tie Front | C11: Tops & blouses | D11: 54.95 | E11: =IFERROR(INDEX(Tiers!$B$4:$B$15,MATCH(C11,Tiers!$A$4:$A$15,0)),D11) -> 44.95 | G11: =IF(F11="",E11,F11) -> 44.95 | H11: =G11-D11 -> -10 | I11: =IFERROR((G11-D11)/D11,0) -> -0.18198362 | J11: =IF(G11>D11,"Omhoog",IF(G11<D11,"Omlaag","Gelijk")) -> Omlaag | K11: =IF(ABS(I11)>=0.2,"controleren","") | L11: =G11*Tiers!$B$19 -> 27.909455 | M11: 99.91 | N11: =IFERROR(1-D11/M11,0) -> 0.450005 | O11: =IF(Tiers!$B$18="ja",Tiers!$B$20,N11) -> 0.450005 | P11: =ROUNDUP(G11/(1-O11),0)-0.05 -> 81.95 | Q11: =IFERROR(1-G11/P11,0) -> 0.45149481 | R11: 48
A12: womens-blouse-peter-pan-collar-button-front-linen | B12: Women's Blouse | Peter Pan Collar Button Front Linen | C12: Tops & blouses | D12: 49.95 | E12: =IFERROR(INDEX(Tiers!$B$4:$B$15,MATCH(C12,Tiers!$A$4:$A$15,0)),D12) -> 44.95 | G12: =IF(F12="",E12,F12) -> 44.95 | H12: =G12-D12 -> -5 | I12: =IFERROR((G12-D12)/D12,0) -> -0.1001001 | J12: =IF(G12>D12,"Omhoog",IF(G12<D12,"Omlaag","Gelijk")) -> Omlaag | K12: =IF(ABS(I12)>=0.2,"controleren","") | L12: =G12*Tiers!$B$19 -> 27.909455 | M12: 83.25 | N12: =IFERROR(1-D12/M12,0) -> 0.4 | O12: =IF(Tiers!$B$18="ja",Tiers!$B$20,N12) -> 0.4 | P12: =ROUNDUP(G12/(1-O12),0)-0.05 -> 74.95 | Q12: =IFERROR(1-G12/P12,0) -> 0.40026684 | R12: 20
A13: womens-blouse-ruffle-sleeve-floral-print-v-neck | B13: Women's Blouse | Ruffle Sleeve Floral Print V-Neck | C13: Tops & blouses | D13: 49.95 | E13: =IFERROR(INDEX(Tiers!$B$4:$B$15,MATCH(C13,Tiers!$A$4:$A$15,0)),D13) -> 44.95 | G13: =IF(F13="",E13,F13) -> 44.95 | H13: =G13-D13 -> -5 | I13: =IFERROR((G13-D13)/D13,0) -> -0.1001001 | J13: =IF(G13>D13,"Omhoog",IF(G13<D13,"Omlaag","Gelijk")) -> Omlaag | K13: =IF(ABS(I13)>=0.2,"controleren","") | L13: =G13*Tiers!$B$19 -> 27.909455 | M13: 83.25 | N13: =IFERROR(1-D13/M13,0) -> 0.4 | O13: =IF(Tiers!$B$18="ja",Tiers!$B$20,N13) -> 0.4 | P13: =ROUNDUP(G13/(1-O13),0)-0.05 -> 74.95 | Q13: =IFERROR(1-G13/P13,0) -> 0.40026684 | R13: 60
A14: womens-blouse-v-neck-short-sleeve-relaxed-fit-1 | B14: Women's Blouse | V-Neck Short Sleeve Relaxed Fit | C14: Tops & blouses | D14: 49.95 | E14: =IFERROR(INDEX(Tiers!$B$4:$B$15,MATCH(C14,Tiers!$A$4:$A$15,0)),D14) -> 44.95 | G14: =IF(F14="",E14,F14) -> 44.95 | H14: =G14-D14 -> -5 | I14: =IFERROR((G14-D14)/D14,0) -> -0.1001001 | J14: =IF(G14>D14,"Omhoog",IF(G14<D14,"Omlaag","Gelijk")) -> Omlaag | K14: =IF(ABS(I14)>=0.2,"controleren","") | L14: =G14*Tiers!$B$19 -> 27.909455 | M14: 83.25 | N14: =IFERROR(1-D14/M14,0) -> 0.4 | O14: =IF(Tiers!$B$18="ja",Tiers!$B$20,N14) -> 0.4 | P14: =ROUNDUP(G14/(1-O14),0)-0.05 -> 74.95 | Q14: =IFERROR(1-G14/P14,0) -> 0.40026684 | R14: 25
A15: womens-blouse-v-neck-short-sleeve-relaxed-fit | B15: Women's Blouse | V-Neck Short Sleeve Relaxed Fit | C15: Tops & blouses | D15: 39.95 | E15: =IFERROR(INDEX(Tiers!$B$4:$B$15,MATCH(C15,Tiers!$A$4:$A$15,0)),D15) -> 44.95 | G15: =IF(F15="",E15,F15) -> 44.95 | H15: =G15-D15 -> 5 | I15: =IFERROR((G15-D15)/D15,0) -> 0.12515645 | J15: =IF(G15>D15,"Omhoog",IF(G15<D15,"Omlaag","Gelijk")) -> Omhoog | K15: =IF(ABS(I15)>=0.2,"controleren","") | L15: =G15*Tiers!$B$19 -> 27.909455 | M15: 66.58 | N15: =IFERROR(1-D15/M15,0) -> 0.39996996 | O15: =IF(Tiers!$B$18="ja",Tiers!$B$20,N15) -> 0.39996996 | P15: =ROUNDUP(G15/(1-O15),0)-0.05 -> 74.95 | Q15: =IFERROR(1-G15/P15,0) -> 0.40026684 | R15: 40
... A319: womens-denim-jacket-stud-embellished-collar-button-front | B319: Women's Denim Jacket | Stud Embellished Collar Button Front | C319: Outerwear | D319: 84.95 | E319: =IFERROR(INDEX(Tiers!$B$4:$B$15,MATCH(C319,Tiers!$A$4:$A$15,0)),D319) -> 74.95 | G319: =IF(F319="",E319,F319) -> 74.95 | H319: =G319-D319 -> -10 | I319: =IFERROR((G319-D319)/D319,0) -> -0.1177163 | J319: =IF(G319>D319,"Omhoog",IF(G319<D319,"Omlaag","Gelijk")) -> Omlaag | K319: =IF(ABS(I319)>=0.2,"controleren","") | L319: =G319*Tiers!$B$19 -> 46.536455 | M319: 141.58 | N319: =IFERROR(1-D319/M319,0) -> 0.39998587 | O319: =IF(Tiers!$B$18="ja",Tiers!$B$20,N319) -> 0.39998587 | P319: =ROUNDUP(G319/(1-O319),0)-0.05 -> 124.95 | Q319: =IFERROR(1-G319/P319,0) -> 0.40016006 | R319: 12

Sheet Samenvatting
A1: LGB — samenvatting prijsvoorstel
A3: Groep | B3: Producten | C3: Gem. nu | D3: Gem. nieuw | E3: Verschil | F3: Omhoog | G3: Omlaag | H3: Gelijk | I3: Te controleren
A4: Tops & blouses | B4: =COUNTIF(Voorstel!$C$4:$C$319,A4) -> 71 | C4: =IFERROR(AVERAGEIF(Voorstel!$C$4:$C$319,A4,Voorstel!$D$4:$D$319),0) -> 47.062676 | D4: =IFERROR(AVERAGEIF(Voorstel!$C$4:$C$319,A4,Voorstel!$G$4:$G$319),0) -> 44.95 | E4: =D4-C4 -> -2.1126761 | F4: =COUNTIFS(Voorstel!$C$4:$C$319,A4,Voorstel!$J$4:$J$319,"Omhoog") -> 9 | G4: =COUNTIFS(Voorstel!$C$4:$C$319,A4,Voorstel!$J$4:$J$319,"Omlaag") -> 18 | H4: =COUNTIFS(Voorstel!$C$4:$C$319,A4,Voorstel!$J$4:$J$319,"Gelijk") -> 44 | I4: =COUNTIFS(Voorstel!$C$4:$C$319,A4,Voorstel!$K$4:$K$319,"controleren") -> 13
A5: Swimwear | B5: =COUNTIF(Voorstel!$C$4:$C$319,A5) -> 5 | C5: =IFERROR(AVERAGEIF(Voorstel!$C$4:$C$319,A5,Voorstel!$D$4:$D$319),0) -> 44.95 | D5: =IFERROR(AVERAGEIF(Voorstel!$C$4:$C$319,A5,Voorstel!$G$4:$G$319),0) -> 44.95 | E5: =D5-C5 -> 0 | F5: =COUNTIFS(Voorstel!$C$4:$C$319,A5,Voorstel!$J$4:$J$319,"Omhoog") -> 0 | G5: =COUNTIFS(Voorstel!$C$4:$C$319,A5,Voorstel!$J$4:$J$319,"Omlaag") -> 0 | H5: =COUNTIFS(Voorstel!$C$4:$C$319,A5,Voorstel!$J$4:$J$319,"Gelijk") -> 5 | I5: =COUNTIFS(Voorstel!$C$4:$C$319,A5,Voorstel!$K$4:$K$319,"controleren") -> 0
A6: Shorts & rokken | B6: =COUNTIF(Voorstel!$C$4:$C$319,A6) -> 28 | C6: =IFERROR(AVERAGEIF(Voorstel!$C$4:$C$319,A6,Voorstel!$D$4:$D$319),0) -> 45.664286 | D6: =IFERROR(AVERAGEIF(Voorstel!$C$4:$C$319,A6,Voorstel!$G$4:$G$319),0) -> 44.95 | E6: =D6-C6 -> -0.71428571 | F6: =COUNTIFS(Voorstel!$C$4:$C$319,A6,Voorstel!$J$4:$J$319,"Omhoog") -> 1 | G6: =COUNTIFS(Voorstel!$C$4:$C$319,A6,Voorstel!$J$4:$J$319,"Omlaag") -> 2 | H6: =COUNTIFS(Voorstel!$C$4:$C$319,A6,Voorstel!$J$4:$J$319,"Gelijk") -> 25 | I6: =COUNTIFS(Voorstel!$C$4:$C$319,A6,Voorstel!$K$4:$K$319,"controleren") -> 2
A7: Sandalen & slippers | B7: =COUNTIF(Voorstel!$C$4:$C$319,A7) -> 26 | C7: =IFERROR(AVERAGEIF(Voorstel!$C$4:$C$319,A7,Voorstel!$D$4:$D$319),0) -> 54.757692 | D7: =IFERROR(AVERAGEIF(Voorstel!$C$4:$C$319,A7,Voorstel!$G$4:$G$319),0) -> 49.95 | E7: =D7-C7 -> -4.8076923 | F7: =COUNTIFS(Voorstel!$C$4:$C$319,A7,Voorstel!$J$4:$J$319,"Omhoog") -> 0 | G7: =COUNTIFS(Voorstel!$C$4:$C$319,A7,Voorstel!$J$4:$J$319,"Omlaag") -> 25 | H7: =COUNTIFS(Voorstel!$C$4:$C$319,A7,Voorstel!$J$4:$J$319,"Gelijk") -> 1 | I7: =COUNTIFS(Voorstel!$C$4:$C$319,A7,Voorstel!$K$4:$K$319,"controleren") -> 0
A8: Broeken | B8: =COUNTIF(Voorstel!$C$4:$C$319,A8) -> 9 | C8: =IFERROR(AVERAGEIF(Voorstel!$C$4:$C$319,A8,Voorstel!$D$4:$D$319),0) -> 56.616667 | D8: =IFERROR(AVERAGEIF(Voorstel!$C$4:$C$319,A8,Voorstel!$G$4:$G$319),0) -> 54.95 | E8: =D8-C8 -> -1.6666667 | F8: =COUNTIFS(Voorstel!$C$4:$C$319,A8,Voorstel!$J$4:$J$319,"Omhoog") -> 1 | G8: =COUNTIFS(Voorstel!$C$4:$C$319,A8,Voorstel!$J$4:$J$319,"Omlaag") -> 5 | H8: =COUNTIFS(Voorstel!$C$4:$C$319,A8,Voorstel!$J$4:$J$319,"Gelijk") -> 3 | I8: =COUNTIFS(Voorstel!$C$4:$C$319,A8,Voorstel!$K$4:$K$319,"controleren") -> 1
A9: Knitwear & cardigans | B9: =COUNTIF(Voorstel!$C$4:$C$319,A9) -> 6 | C9: =IFERROR(AVERAGEIF(Voorstel!$C$4:$C$319,A9,Voorstel!$D$4:$D$319),0) -> 59.95 | D9: =IFERROR(AVERAGEIF(Voorstel!$C$4:$C$319,A9,Voorstel!$G$4:$G$319),0) -> 54.95 | E9: =D9-C9 -> -5 | F9: =COUNTIFS(Voorstel!$C$4:$C$319,A9,Voorstel!$J$4:$J$319,"Omhoog") -> 0 | G9: =COUNTIFS(Voorstel!$C$4:$C$319,A9,Voorstel!$J$4:$J$319,"Omlaag") -> 6 | H9: =COUNTIFS(Voorstel!$C$4:$C$319,A9,Voorstel!$J$4:$J$319,"Gelijk") -> 0 | I9: =COUNTIFS(Voorstel!$C$4:$C$319,A9,Voorstel!$K$4:$K$319,"controleren") -> 0
A10: Platte schoenen & loafers | B10: =COUNTIF(Voorstel!$C$4:$C$319,A10) -> 24 | C10: =IFERROR(AVERAGEIF(Voorstel!$C$4:$C$319,A10,Voorstel!$D$4:$D$319),0) -> 62.866667 | D10: =IFERROR(AVERAGEIF(Voorstel!$C$4:$C$319,A10,Voorstel!$G$4:$G$319),0) -> 54.95 | E10: =D10-C10 -> -7.9166667 | F10: =COUNTIFS(Voorstel!$C$4:$C$319,A10,Voorstel!$J$4:$J$319,"Omhoog") -> 0 | G10: =COUNTIFS(Voorstel!$C$4:$C$319,A10,Voorstel!$J$4:$J$319,"Omlaag") -> 22 | H10: =COUNTIFS(Voorstel!$C$4:$C$319,A10,Voorstel!$J$4:$J$319,"Gelijk") -> 2 | I10: =COUNTIFS(Voorstel!$C$4:$C$319,A10,Voorstel!$K$4:$K$319,"controleren") -> 0
A11: Jurken | B11: =COUNTIF(Voorstel!$C$4:$C$319,A11) -> 107 | C11: =IFERROR(AVERAGEIF(Voorstel!$C$4:$C$319,A11,Voorstel!$D$4:$D$319),0) -> 68.12757 | D11: =IFERROR(AVERAGEIF(Voorstel!$C$4:$C$319,A11,Voorstel!$G$4:$G$319),0) -> 59.95 | E11: =D11-C11 -> -8.1775701 | F11: =COUNTIFS(Voorstel!$C$4:$C$319,A11,Voorstel!$J$4:$J$319,"Omhoog") -> 8 | G11: =COUNTIFS(Voorstel!$C$4:$C$319,A11,Voorstel!$J$4:$J$319,"Omlaag") -> 97 | H11: =COUNTIFS(Voorstel!$C$4:$C$319,A11,Voorstel!$J$4:$J$319,"Gelijk") -> 2 | I11: =COUNTIFS(Voorstel!$C$4:$C$319,A11,Voorstel!$K$4:$K$319,"controleren") -> 4
A12: Hakken | B12: =COUNTIF(Voorstel!$C$4:$C$319,A12) -> 15 | C12: =IFERROR(AVERAGEIF(Voorstel!$C$4:$C$319,A12,Voorstel!$D$4:$D$319),0) -> 64.95 | D12: =IFERROR(AVERAGEIF(Voorstel!$C$4:$C$319,A12,Voorstel!$G$4:$G$319),0) -> 59.95 | E12: =D12-C12 -> -5 | F12: =COUNTIFS(Voorstel!$C$4:$C$319,A12,Voorstel!$J$4:$J$319,"Omhoog") -> 0 | G12: =COUNTIFS(Voorstel!$C$4:$C$319,A12,Voorstel!$J$4:$J$319,"Omlaag") -> 15 | H12: =COUNTIFS(Voorstel!$C$4:$C$319,A12,Voorstel!$J$4:$J$319,"Gelijk") -> 0 | I12: =COUNTIFS(Voorstel!$C$4:$C$319,A12,Voorstel!$K$4:$K$319,"controleren") -> 0
A13: Sneakers | B13: =COUNTIF(Voorstel!$C$4:$C$319,A13) -> 4 | C13: =IFERROR(AVERAGEIF(Voorstel!$C$4:$C$319,A13,Voorstel!$D$4:$D$319),0) -> 69.95 | D13: =IFERROR(AVERAGEIF(Voorstel!$C$4:$C$319,A13,Voorstel!$G$4:$G$319),0) -> 59.95 | E13: =D13-C13 -> -10 | F13: =COUNTIFS(Voorstel!$C$4:$C$319,A13,Voorstel!$J$4:$J$319,"Omhoog") -> 0 | G13: =COUNTIFS(Voorstel!$C$4:$C$319,A13,Voorstel!$J$4:$J$319,"Omlaag") -> 4 | H13: =COUNTIFS(Voorstel!$C$4:$C$319,A13,Voorstel!$J$4:$J$319,"Gelijk") -> 0 | I13: =COUNTIFS(Voorstel!$C$4:$C$319,A13,Voorstel!$K$4:$K$319,"controleren") -> 0
A14: Boots | B14: =COUNTIF(Voorstel!$C$4:$C$319,A14) -> 13 | C14: =IFERROR(AVERAGEIF(Voorstel!$C$4:$C$319,A14,Voorstel!$D$4:$D$319),0) -> 78.411538 | D14: =IFERROR(AVERAGEIF(Voorstel!$C$4:$C$319,A14,Voorstel!$G$4:$G$319),0) -> 69.95 | E14: =D14-C14 -> -8.4615385 | F14: =COUNTIFS(Voorstel!$C$4:$C$319,A14,Voorstel!$J$4:$J$319,"Omhoog") -> 1 | G14: =COUNTIFS(Voorstel!$C$4:$C$319,A14,Voorstel!$J$4:$J$319,"Omlaag") -> 12 | H14: =COUNTIFS(Voorstel!$C$4:$C$319,A14,Voorstel!$J$4:$J$319,"Gelijk") -> 0 | I14: =COUNTIFS(Voorstel!$C$4:$C$319,A14,Voorstel!$K$4:$K$319,"controleren") -> 0
A15: Outerwear | B15: =COUNTIF(Voorstel!$C$4:$C$319,A15) -> 8 | C15: =IFERROR(AVERAGEIF(Voorstel!$C$4:$C$319,A15,Voorstel!$D$4:$D$319),0) -> 86.825 | D15: =IFERROR(AVERAGEIF(Voorstel!$C$4:$C$319,A15,Voorstel!$G$4:$G$319),0) -> 74.95 | E15: =D15-C15 -> -11.875 | F15: =COUNTIFS(Voorstel!$C$4:$C$319,A15,Voorstel!$J$4:$J$319,"Omhoog") -> 1 | G15: =COUNTIFS(Voorstel!$C$4:$C$319,A15,Voorstel!$J$4:$J$319,"Omlaag") -> 7 | H15: =COUNTIFS(Voorstel!$C$4:$C$319,A15,Voorstel!$J$4:$J$319,"Gelijk") -> 0 | I15: =COUNTIFS(Voorstel!$C$4:$C$319,A15,Voorstel!$K$4:$K$319,"controleren") -> 0
A16: Totaal | B16: =SUM(B4:B15) -> 316 | C16: =IFERROR(AVERAGE(Voorstel!$D$4:$D$319),0) -> 59.823418 | D16: =IFERROR(AVERAGE(Voorstel!$G$4:$G$319),0) -> 54.364557 | E16: =D16-C16 -> -5.4588608 | F16: =SUM(F4:F15) -> 21 | G16: =SUM(G4:G15) -> 213 | H16: =SUM(H4:H15) -> 82 | I16: =SUM(I4:I15) -> 20
A18: Laagste prijs nu | B18: =MIN(Voorstel!$D$4:$D$319) -> 34.95
A19: Hoogste prijs nu | B19: =MAX(Voorstel!$D$4:$D$319) -> 89.95
A20: Laagste prijs nieuw | B20: =MIN(Voorstel!$G$4:$G$319) -> 44.95
A21: Hoogste prijs nieuw | B21: =MAX(Voorstel!$G$4:$G$319) -> 74.95
A22: Gem. prijs nieuw in euro | B22: =D16*Tiers!$B$19 -> 33.754953
A23: Gem. korting nu | B23: =IFERROR(AVERAGE(Voorstel!$N$4:$N$319),0) -> 0.44746954
A24: Gem. korting nieuw | B24: =IFERROR(AVERAGE(Voorstel!$Q$4:$Q$319),0) -> 0.44811767
A26: Opmerkingen
A27: Doel is conversie: de prijsband gaat van A$34,95–A$89,95 naar A$44,95–A$74,95, met het zwaartepunt op A$44,95–A$59,95.
A28: De 107 jurken zijn de grootste hefboom. Die stonden op A$69,95 en gaan naar A$59,95 — dat is waar de meeste conversiewinst zit.
A29: De vloer blijft A$44,95 (ongeveer 28 euro). Lager wordt het winstarm: zie het tabblad Marge, bij ROAS 2,0 houd je daar nog maar een paar dollar per order over.
A30: Het plafond gaat naar A$74,95 voor jassen. Boven de A$75 zakt de conversie in deze categorie en LGB heeft nog geen merkvertrouwen om dat te dragen.
A31: Compare-at houdt per product hetzelfde kortingspercentage als nu, tenzij je in Tiers de uniforme korting aanzet. Omdat de prijzen zakken, zakt de doorstreepprijs mee.
A32: GMC-risico, hetzelfde als bij SSB: elk product staat op een vaste 40/45/50% korting. Een doorstreepprijs die nooit de echte verkoopprijs was, is in Google Shopping een overtreding.
A33: 15 producten hebben "Men's" in de titel terwijl LGB een dames-store is (o.a. Men's Closed Toe Sandals, Men's Cardigan, Men's Tailored Dress Shorts). Los van de prijs: dat wil je opruimen of het gender-attribuut goed zetten, anders kost het je zichtbaarheid in Shopping.
A34: Deze sheet raakt de store niet. Na jouw goedkeuring voer ik het door via de Shopify API.

Sheet Marge
A1: LGB — hoeveel houd je over per order?
A2: Vul de gele cellen met je eigen cijfers. Alles eronder rekent mee.
A4: Inkoopprijs als % van de verkoopprijs (COGS) | B4: 0.3
A5: ROAS (omzet gedeeld door ad spend) | B5: 2.2
A6: Betaalkosten als % van de verkoopprijs | B6: 0.03
A7: Refunds en retouren als % van de omzet | B7: 0.04
A9: Ad spend als % van de omzet | B9: =IFERROR(1/B5,0) -> 0.45454545
A10: Marge die overblijft als % van de prijs | B10: =1-B4-B9-B6-B7 -> 0.17545455
A12: Per prijspunt
A13: Prijs (AUD) | B13: In euro | C13: Inkoop | D13: Ad spend | E13: Betaalkosten | F13: Refunds | G13: Blijft over | H13: Blijft over %
A14: 39.95 | B14: =A14*Tiers!$B$19 -> 24.804955 | C14: =A14*$B$4 -> 11.985 | D14: =A14*$B$9 -> 18.159091 | E14: =A14*$B$6 -> 1.1985 | F14: =A14*$B$7 -> 1.598 | G14: =A14-C14-D14-E14-F14 -> 7.0094091 | H14: =IFERROR(G14/A14,0) -> 0.17545455
A15: 44.95 | B15: =A15*Tiers!$B$19 -> 27.909455 | C15: =A15*$B$4 -> 13.485 | D15: =A15*$B$9 -> 20.431818 | E15: =A15*$B$6 -> 1.3485 | F15: =A15*$B$7 -> 1.798 | G15: =A15-C15-D15-E15-F15 -> 7.8866818 | H15: =IFERROR(G15/A15,0) -> 0.17545455
A16: 49.95 | B16: =A16*Tiers!$B$19 -> 31.013955 | C16: =A16*$B$4 -> 14.985 | D16: =A16*$B$9 -> 22.704545 | E16: =A16*$B$6 -> 1.4985 | F16: =A16*$B$7 -> 1.998 | G16: =A16-C16-D16-E16-F16 -> 8.7639545 | H16: =IFERROR(G16/A16,0) -> 0.17545455
A17: 54.95 | B17: =A17*Tiers!$B$19 -> 34.118455 | C17: =A17*$B$4 -> 16.485 | D17: =A17*$B$9 -> 24.977273 | E17: =A17*$B$6 -> 1.6485 | F17: =A17*$B$7 -> 2.198 | G17: =A17-C17-D17-E17-F17 -> 9.6412273 | H17: =IFERROR(G17/A17,0) -> 0.17545455
A18: 59.95 | B18: =A18*Tiers!$B$19 -> 37.222955 | C18: =A18*$B$4 -> 17.985 | D18: =A18*$B$9 -> 27.25 | E18: =A18*$B$6 -> 1.7985 | F18: =A18*$B$7 -> 2.398 | G18: =A18-C18-D18-E18-F18 -> 10.5185 | H18: =IFERROR(G18/A18,0) -> 0.17545455
A19: 64.95 | B19: =A19*Tiers!$B$19 -> 40.327455 | C19: =A19*$B$4 -> 19.485 | D19: =A19*$B$9 -> 29.522727 | E19: =A19*$B$6 -> 1.9485 | F19: =A19*$B$7 -> 2.598 | G19: =A19-C19-D19-E19-F19 -> 11.395773 | H19: =IFERROR(G19/A19,0) -> 0.17545455
A20: 69.95 | B20: =A20*Tiers!$B$19 -> 43.431955 | C20: =A20*$B$4 -> 20.985 | D20: =A20*$B$9 -> 31.795455 | E20: =A20*$B$6 -> 2.0985 | F20: =A20*$B$7 -> 2.798 | G20: =A20-C20-D20-E20-F20 -> 12.273045 | H20: =IFERROR(G20/A20,0) -> 0.17545455
A21: 74.95 | B21: =A21*Tiers!$B$19 -> 46.536455 | C21: =A21*$B$4 -> 22.485 | D21: =A21*$B$9 -> 34.068182 | E21: =A21*$B$6 -> 2.2485 | F21: =A21*$B$7 -> 2.998 | G21: =A21-C21-D21-E21-F21 -> 13.150318 | H21: =IFERROR(G21/A21,0) -> 0.17545455
A22: 79.95 | B22: =A22*Tiers!$B$19 -> 49.640955 | C22: =A22*$B$4 -> 23.985 | D22: =A22*$B$9 -> 36.340909 | E22: =A22*$B$6 -> 2.3985 | F22: =A22*$B$7 -> 3.198 | G22: =A22-C22-D22-E22-F22 -> 14.027591 | H22: =IFERROR(G22/A22,0) -> 0.17545455
A24: Hoe je dit leest
A25: De percentages zijn aannames, geen gemeten cijfers. COGS 30% komt uit de TrackBee-fallback en is dus een schatting — de Kungfubuy-bills zijn de echte bron.
A26: ROAS 2,2 is het niveau waar SSB op zat in de RTM-benchmark (11 aug–15 sep 2026: ongeveer 2,5 op de actieve campagnes).
A27: Dit is contributiemarge per order: er gaan nog geen vaste kosten, apps, mediabuyer-fee of chargebacks af.
A28: De vloer van A$44,95 in het voorstel komt hieruit: zak je daaronder, dan verdien je bij deze ROAS niet genoeg per order om de rest te dekken.
